vscdark/__init__.py
vscdark/vscdark.mplstyle
vscdark/vscdark.py
vscdark/vsclight.mplstyle
vscdark-0.3.3.dist-info/LICENSE
vscdark-0.3.3.dist-info/METADATA
vscdark-0.3.3.dist-info/WHEEL
vscdark-0.3.3.dist-info/RECORD
