Metadata-Version: 2.3
Name: vscdark
Version: 0.3.3
Summary: Matplotlib and Ipywidgets dark theme/styling that fits well with VSCode
Author: Lorenz Kies
Author-email: dev@lkies.net
Requires-Python: >=3.10
Classifier: Programming Language :: Python :: 3
Classifier: Programming Language :: Python :: 3.10
Classifier: Programming Language :: Python :: 3.11
Classifier: Programming Language :: Python :: 3.12
Classifier: Programming Language :: Python :: 3.13
